whnacos/__init__.py
whnacos/config.py
whale_nacos-0.4.2.dist-info/METADATA
whale_nacos-0.4.2.dist-info/WHEEL
whale_nacos-0.4.2.dist-info/top_level.txt
whale_nacos-0.4.2.dist-info/RECORD
