Metadata-Version: 2.1
Name: whale-nacos
Version: 0.4.2
Summary: whale nacos sdk
Author: Joey
Author-email: yizhao@whale.im
Requires-Python: >=3.5
Requires-Dist: nacos-sdk-python
Requires-Dist: grpcio
